data_visualizer/__init__.py
data_visualizer/alerts.py
data_visualizer/correlations.py
data_visualizer/profiler.py
data_visualizer/report.py
data_visualizer/settings.py
data_visualizer/type_analyzers.py
data_visualizer/type_registry.py
data_visualizer/visualizer.py
data_visualizer/templates/report.html
pydata_visualizer-1.0.2.dist-info/licenses/LICENSE
pydata_visualizer-1.0.2.dist-info/METADATA
pydata_visualizer-1.0.2.dist-info/WHEEL
pydata_visualizer-1.0.2.dist-info/top_level.txt
pydata_visualizer-1.0.2.dist-info/RECORD
