Metadata-Version: 2.4
Name: Pydata-visualizer
Version: 1.0.2
Summary: A Python library for Exploratory Data Analysis and Profiling.
Author-email: Aditya Deshmukh <adideshmukh2005@gmail.com>
License: MIT
Project-URL: Homepage, https://github.com/Adi-Deshmukh/Pydata-visualizer
Project-URL: Documentation, https://pydata-visualizer.readthedocs.io/en/latest/
Project-URL: Bug Tracker, https://github.com/Adi-Deshmukh/Pydata-visualizer/issues
Project-URL: Source Code, https://github.com/Adi-Deshmukh/Pydata-visualizer
Classifier: Programming Language :: Python :: 3
Classifier: Operating System :: OS Independent
Requires-Python: >=3.8
License-File: LICENSE
Requires-Dist: imagehash
Requires-Dist: Jinja2
Requires-Dist: matplotlib
Requires-Dist: numpy
Requires-Dist: pandas
Requires-Dist: pydantic
Requires-Dist: scipy
Requires-Dist: seaborn
Requires-Dist: shapely
Requires-Dist: visions[complete]
Requires-Dist: tqdm
Requires-Dist: colorama
Requires-Dist: wordcloud
Requires-Dist: plotly
Dynamic: license-file
